crillab_metrics-1.3.0.dist-info/METADATA
crillab_metrics-1.3.0.dist-info/WHEEL
crillab_metrics-1.3.0.dist-info/licenses/LICENSE.md
metrics/__init__.py
metrics/core/__init__.py
metrics/core/builder/__init__.py
metrics/core/builder/attribute_manager.py
metrics/core/builder/builder.py
metrics/core/builder/typing_strategy.py
metrics/core/constants.py
metrics/core/model.py
metrics/scalpel/__init__.py
metrics/scalpel/config/__init__.py
metrics/scalpel/config/config.py
metrics/scalpel/config/configsaver.py
metrics/scalpel/config/datafile.py
metrics/scalpel/config/format.py
metrics/scalpel/config/inputset.py
metrics/scalpel/config/wrapper.py
metrics/scalpel/listener.py
metrics/scalpel/parser/__init__.py
metrics/scalpel/parser/campaign.py
metrics/scalpel/parser/output.py
metrics/scalpel/utils/__init__.py
metrics/scalpel/utils/csvutils.py
metrics/scalpel/utils/filters.py
metrics/scalpel/utils/logging.py
metrics/scalpel/utils/pattern.py
metrics/studio/__init__.py
metrics/studio/report.py
metrics/studio/scalpelcli.py
metrics/templates/README.md
metrics/templates/gitignore
metrics/templates/load_experiments.ipynb
metrics/templates/load_experiments_optim.ipynb
metrics/templates/load_experiments_sat.ipynb
metrics/templates/optim_analysis.ipynb
metrics/templates/requirements.txt
metrics/templates/runtime_analysis.ipynb
metrics/templates/scalpel_config.yml
metrics/wallet/__init__.py
metrics/wallet/analysis.py
metrics/wallet/plot.py
crillab_metrics-1.3.0.dist-info/RECORD
