Metadata-Version: 2.1
Name: crillab-metrics
Version: 1.3.0
Summary: rEproducible sofTware peRformance analysIs in perfeCt Simplicity
Keywords: reproducible software performance analysis
Author: Thibault Falque, Romain Wallon, Hugues Wattez
Author-Email: Unknown <metrics@cril.fr>
License: LGPLv3+
Classifier: Development Status :: 5 - Production/Stable
Classifier: License :: OSI Approved :: GNU Lesser General Public License v3 or later (LGPLv3+)
Classifier: Operating System :: OS Independent
Classifier: Programming Language :: Python :: 3.8
Project-URL: Homepage, https://github.com/crillab/metrics
Requires-Python: >=3.10
Requires-Dist: InquirerPy
Requires-Dist: crillab-autograph
Requires-Dist: dash-bootstrap-components
Requires-Dist: deprecated
Requires-Dist: jinja2
Requires-Dist: jsonpickle
Requires-Dist: loguru
Requires-Dist: myst-parser
Requires-Dist: pandas
Requires-Dist: pyfiglet
Requires-Dist: pyparsing
Requires-Dist: pyyaml
Requires-Dist: tenacity
